{
  "year": 2025,
  "month": 12,
  "week": "W02",
  "range": "2025-12-07 2025-12-12",
  "items": [
    {
      "name": "김용수",
      "domain": "Frontend",
      "project": "스프레드시트",
      "topic": "셀 렌더링 개선",
      "plan": "셀 렌더링 병목 구간 분석 80% 완료",
      "planPercent": 80,
      "progress": "병목 분석 및 개선안 60% 완료",
      "progressPercent": 60,
      "next": "개선안 적용 및 영향도 테스트 진행",
      "risk": "특정 시트에서 렌더링 지연 재현됨",
      "riskLevel": 2
    },
    {
      "name": "김현",
      "domain": "Frontend",
      "project": "스프레드시트",
      "topic": "셀 렌더링 개선",
      "plan": "셀 최적화 100% 완료",
      "planPercent": 100,
      "progress": "셀 렌더링 구조화 및 개선작업 100% 완료",
      "progressPercent": 100,
      "next": "렌더링 최적화 마무리 및 Publish 테스트 추가",
      "risk": "Publish 플로우에서 race condition 재발 가능성 확인",
      "riskLevel": 1
    },
    {
      "name": "서상준",
      "domain": "Backend",
      "project": "권한 시스템",
      "topic": "접근 제어 UX",
      "plan": "접근 제어 정책 엔드포인트 100% 개발",
      "planPercent": 100,
      "progress": "엔드포인트 개발 및 테스트 90% 완료",
      "progressPercent": 90,
      "next": "프론트 통합 테스트 및 정책 동기화 API 검증",
      "risk": "",
      "riskLevel": 0
    },
    {
      "name": "김희성",
      "domain": "Planning",
      "project": "워크스페이스",
      "topic": "IA 개선",
      "plan": "IA 구조 v1 정리 완료 (100%)",
      "planPercent": 100,
      "progress": "IA 구조 v1 정리 및 워딩 1차 검토 완료 (100%)",
      "progressPercent": 100,
      "next": "IA v1.1 반영 및 기획–개발 매핑 구조 확정",
      "risk": "",
      "riskLevel": 0
    },
    {
      "name": "김태이",
      "domain": "Frontend",
      "project": "워크스페이스",
      "topic": "IA 기반 편집기 설계",
      "plan": "템플릿 편집기 UX 80% 설계",
      "planPercent": 80,
      "progress": "UX 60% 설계 완료",
      "progressPercent": 60,
      "next": "컴포넌트 요구사항 문서화 및 IA 매핑 추가",
      "risk": "일정 대비 이해관계자 요구사항 변동",
      "riskLevel": 2
    },
    {
      "name": "김정빈",
      "domain": "Frontend",
      "project": "공통 라이브러리",
      "topic": "테이블 컴포넌트",
      "plan": "AI Agent 기반 개발 100% 완료",
      "planPercent": 100,
      "progress": "AI Agent 기반 개발 70% 완료",
      "progressPercent": 70,
      "next": "완료하지 못했던 AI Agent 기반 개발 100% 달성",
      "risk": "사내 행사 발표 준비",
      "riskLevel": 2
    },
    {
      "name": "이하영",
      "domain": "Design",
      "project": "대시보드",
      "topic": "UI 시스템 개선",
      "plan": "차트 컴포넌트 UI 70% 완료",
      "planPercent": 70,
      "progress": "라인·바 차트 UI 55% 완료",
      "progressPercent": 55,
      "next": "상호작용 영역 확대 및 데이터 상태별 스타일 정리",
      "risk": "",
      "riskLevel": 0
    },
    {
      "name": "변창언",
      "domain": "Backend",
      "project": "API Gateway",
      "topic": "캐싱 레이어",
      "plan": "캐싱 레이어 100% 구축",
      "planPercent": 100,
      "progress": "Redis 캐싱 레이어 구축 100% 완료",
      "progressPercent": 100,
      "next": "캐시 히트율 모니터링 기능 개발",
      "risk": "",
      "riskLevel": 0
    },
    {
      "name": "손영민",
      "domain": "Frontend",
      "project": "대시보드",
      "topic": "차트 컴포넌트",
      "plan": "D3 기반 차트 60% 구현",
      "planPercent": 60,
      "progress": "라인차트 렌더링 40% 진행중",
      "progressPercent": 40,
      "next": "D3 데이터 스케일링 검토 및 범례 컴포넌트 제작",
      "risk": "",
      "riskLevel": 0
    },
    {
      "name": "김희성",
      "domain": "Planning",
      "project": "온보딩",
      "topic": "고객 플로우 개선",
      "plan": "온보딩 플로우 50% 재정의",
      "planPercent": 50,
      "progress": "온보딩 단계 정의 40% 완료",
      "progressPercent": 40,
      "next": "퍼널 기준 KPI 산정 작업",
      "risk": "주요 지표 산정 기준 확정 지연 가능성",
      "riskLevel": 1
    },
    {
      "name": "조해용",
      "domain": "Content",
      "project": "문서 자동화",
      "topic": "매뉴얼 개편",
      "plan": "매뉴얼 자동화 스크립트 80% 기획",
      "planPercent": 80,
      "progress": "구조 검토 및 샘플 문서 제작 60% 완료",
      "progressPercent": 60,
      "next": "실제 매뉴얼 세트에 자동화 적용 시범 운영",
      "risk": "",
      "riskLevel": 0
    },
    {
      "name": "도기봉",
      "domain": "Backend",
      "project": "인증 서비스",
      "topic": "OAuth 연동",
      "plan": "OAuth 연동 100% 완료",
      "planPercent": 100,
      "progress": "Google OAuth 연동 90% 완료",
      "progressPercent": 90,
      "next": "Apple OAuth 연동 및 토큰 갱신 테스트 추가",
      "risk": "",
      "riskLevel": 1
    },
    {
      "name": "윤재웅",
      "domain": "Planning",
      "project": "제품 전략",
      "topic": "요구사항 정렬",
      "plan": "요구사항 정렬 70% 완료",
      "planPercent": 70,
      "progress": "요구사항 항목 50% 정리 완료",
      "progressPercent": 50,
      "next": "개발팀·디자인팀과 정합성 재검토",
      "risk": "일부 요구사항 우선순위 미정",
      "riskLevel": 2
    },
    {
      "name": "한내경",
      "domain": "Design",
      "project": "워크스페이스",
      "topic": "컴포넌트 라이브러리",
      "plan": "디자인 토큰 100% 정의",
      "planPercent": 100,
      "progress": "토큰 구조 90% 정리 완료",
      "progressPercent": 90,
      "next": "FE와 토큰 매핑 검증",
      "risk": "",
      "riskLevel": 0
    },
    {
      "name": "양소희",
      "domain": "Marketing",
      "project": "랜딩 페이지",
      "topic": "메시지 실험",
      "plan": "AB 테스트 2건 설계 완료",
      "planPercent": 0,
      "progress": "Test A 기획 100%, Test B 기획 50%",
      "progressPercent": 100,
      "next": "개발 전달용 실험 요구서 정리",
      "risk": "고객 샘플 크기 부족 가능성",
      "riskLevel": 1
    },
    {
      "name": "김상리",
      "domain": "Content",
      "project": "교육 콘텐츠",
      "topic": "튜토리얼 작성",
      "plan": "튜토리얼 60% 제작",
      "planPercent": 60,
      "progress": "초안 40% 완성",
      "progressPercent": 40,
      "next": "튜토리얼 영상 스크립트 작성",
      "risk": "",
      "riskLevel": 0
    },
    {
      "name": "김지원",
      "domain": "Frontend",
      "project": "공통 컴포넌트",
      "topic": "디자인 시스템",
      "plan": "Button, Input 컴포넌트 문서화 100% 완료",
      "planPercent": 100,
      "progress": "Storybook 문서화 90% 완료",
      "progressPercent": 90,
      "next": "Modal, Toast 컴포넌트 마이그레이션",
      "risk": "",
      "riskLevel": 0
    },
    {
      "name": "하성열",
      "domain": "Backend",
      "project": "데이터 파이프라인",
      "topic": "로그 스키마 정리",
      "plan": "로그 스키마 80% 정의",
      "planPercent": 80,
      "progress": "주요 이벤트 스키마 60% 정리 완료",
      "progressPercent": 60,
      "next": "ETL 파이프라인에 스키마 적용",
      "risk": "",
      "riskLevel": 0
    }
  ]
}